xontrib/macro_lib/__init__.py
xontrib/macro_lib/data.py
xontrib/macro_lib/docker.py
xontrib/macro_lib/run_once.py
xontrib_macro_lib-0.0.3.dist-info/LICENSE
xontrib_macro_lib-0.0.3.dist-info/METADATA
xontrib_macro_lib-0.0.3.dist-info/WHEEL
xontrib_macro_lib-0.0.3.dist-info/top_level.txt
xontrib_macro_lib-0.0.3.dist-info/RECORD
