Metadata-Version: 2.1
Name: xontrib-macro-lib
Version: 0.0.3
Summary: Library of the useful macroses for the xonsh shell.
Home-page: https://github.com/anki-code/xontrib-macro-lib
Author: anki-code
Author-email: no@no.no
License: MIT
Project-URL: Documentation, https://github.com/anki-code/xontrib-macro-lib/blob/master/README.md
Project-URL: Code, https://github.com/anki-code/xontrib-macro-lib
Project-URL: Issue tracker, https://github.com/anki-code/xontrib-macro-lib/issues
Platform: any
Classifier: Programming Language :: Python :: 3
Classifier: Programming Language :: Python :: 3.6
Classifier: Programming Language :: Python :: 3.7
Classifier: Programming Language :: Python :: 3.8
Classifier: Programming Language :: Python :: 3.9
Classifier: License :: OSI Approved :: MIT License
Classifier: Operating System :: OS Independent
Classifier: Topic :: System :: Shells
Classifier: Topic :: System :: System Shells
Classifier: Topic :: Terminals
Requires-Python: >=3.6
Requires-Dist: xonsh
